.pylintrc
CHANGELOG.md
LICENSE.txt
MANIFEST.in
README.md
conftest.py
invoke.yaml
requirements.txt
setup.cfg
setup.py
tasks.py
dploy/__init__.py
dploy/__init__.pyc
dploy/__main__.py
dploy/actions.py
dploy/cli.py
dploy/errors.py
dploy/main.py
dploy/utils.py
dploy/version.py
dploy.egg-info/PKG-INFO
dploy.egg-info/SOURCES.txt
dploy.egg-info/dependency_links.txt
dploy.egg-info/entry_points.txt
dploy.egg-info/top_level.txt
dploy/__pycache__/__init__.cpython-33.pyc
dploy/__pycache__/__init__.cpython-35.pyc
dploy/__pycache__/__main__.cpython-33.pyc
dploy/__pycache__/__main__.cpython-35.pyc
dploy/__pycache__/actions.cpython-33.pyc
dploy/__pycache__/actions.cpython-35.pyc
dploy/__pycache__/cli.cpython-33.pyc
dploy/__pycache__/cli.cpython-35.pyc
dploy/__pycache__/errors.cpython-33.pyc
dploy/__pycache__/errors.cpython-35.pyc
dploy/__pycache__/main.cpython-33.pyc
dploy/__pycache__/main.cpython-35.pyc
dploy/__pycache__/utils.cpython-33.pyc
dploy/__pycache__/utils.cpython-35.pyc
dploy/__pycache__/version.cpython-33.pyc
dploy/__pycache__/version.cpython-35.pyc
tests/conftest.py
tests/test_cli.py
tests/test_ignore.py
tests/test_link.py
tests/test_stow.py
tests/test_unstow.py
tests/utils.py
tests/__pycache__/conftest.cpython-33-PYTEST.pyc
tests/__pycache__/conftest.cpython-33.pyc
tests/__pycache__/conftest.cpython-35.pyc
tests/__pycache__/test_cli.cpython-33-PYTEST.pyc
tests/__pycache__/test_cli.cpython-35-PYTEST.pyc
tests/__pycache__/test_ignore.cpython-33-PYTEST.pyc
tests/__pycache__/test_ignore.cpython-35-PYTEST.pyc
tests/__pycache__/test_link.cpython-33-PYTEST.pyc
tests/__pycache__/test_link.cpython-35-PYTEST.pyc
tests/__pycache__/test_stow.cpython-33-PYTEST.pyc
tests/__pycache__/test_stow.cpython-35-PYTEST.pyc
tests/__pycache__/test_unstow.cpython-33-PYTEST.pyc
tests/__pycache__/test_unstow.cpython-35-PYTEST.pyc
tests/__pycache__/utils.cpython-33.pyc
tests/__pycache__/utils.cpython-35.pyc