Metadata-Version: 1.1
Name: dploy
Version: 0.1.1
Summary: 
